module/__init__.py
module/great.py
ilyavtln_py-0.0.2.dist-info/METADATA
ilyavtln_py-0.0.2.dist-info/WHEEL
ilyavtln_py-0.0.2.dist-info/top_level.txt
ilyavtln_py-0.0.2.dist-info/RECORD
