Metadata-Version: 2.1
Name: ilyavtln_py
Version: 0.0.2
Summary: A personal python package
Home-page: https://github.com/ilyavtln/ilyavtln_py
Author: Vatlin Ilya
Author-email: ilyavtln@gmail.com
License: MIT
Classifier: Programming Language :: Python :: 3
Classifier: License :: OSI Approved :: MIT License
Classifier: Operating System :: OS Independent
Requires-Python: >=3.7
